atomic_write_path/__init__.py
atomic_write_path/atomic_write_path.py
atomic_write_path-1.4.4.dist-info/METADATA
atomic_write_path-1.4.4.dist-info/WHEEL
atomic_write_path-1.4.4.dist-info/top_level.txt
atomic_write_path-1.4.4.dist-info/RECORD
