Metadata-Version: 2.1
Name: atomic-write-path
Version: 1.4.4
Summary: Provides the `atomic-write-path` context manager
Home-page: UNKNOWN
Author: Bao Wei
Author-email: baowei.ur521@gmail.com
License: MIT
Platform: UNKNOWN
Requires-Python: >=3.8
Requires-Dist: atomicwrites (==1.4.*)
